Metadata-Version: 2.3
Name: mcp-server-perplexity
Version: 0.1.2
Summary: MCP Server for the Perplexity API.
Project-URL: Homepage, https://github.com/tanigami/mcp-server-perplexity
Project-URL: Repository, https://github.com/tanigami/mcp-server-perplexity
Author-email: Hirofumi Tanigami <tanigami@teps.io>
Requires-Python: >=3.10
Requires-Dist: mcp>=1.0.0
